test_tele/0_👋_Hello.py
test_tele/__init__.py
test_tele/bot/__init__.py
test_tele/bot/live_bot.py
test_tele/bot/utils.py
test_tele/cli.py
test_tele/config.py
test_tele/const.py
test_tele/live.py
test_tele/pages/1_🔑_Telegram_Login.py
test_tele/pages/2_⭐_Admins.py
test_tele/pages/3_🔗_Connections.py
test_tele/pages/4_🔌_Plugins.py
test_tele/pages/5_🏃_Run.py
test_tele/pages/6_🔬_Advanced.py
test_tele/password.py
test_tele/past.py
test_tele/plugin_models.py
test_tele/plugins/__init__.py
test_tele/plugins/caption.py
test_tele/plugins/filter.py
test_tele/plugins/fmt.py
test_tele/plugins/mark.py
test_tele/plugins/ocr.py
test_tele/plugins/replace.py
test_tele/plugins/special.py
test_tele/run.py
test_tele/storage.py
test_tele/utils.py
test_tele/utils_webui.py
test_tele-0.1.3.6.dist-info/entry_points.txt
test_tele-0.1.3.6.dist-info/LICENSE
test_tele-0.1.3.6.dist-info/METADATA
test_tele-0.1.3.6.dist-info/WHEEL
test_tele-0.1.3.6.dist-info/RECORD
