Metadata-Version: 2.1
Name: test-tele
Version: 0.1.3.6
Summary: test tele bot, [beta] support topic
Home-page: https://github.com/aahnik/tgcf
License: MIT
Author: aahnik
Author-email: daw@aahnik.dev
Requires-Python: >=3.10,<4.0
Classifier: License :: OSI Approved :: MIT License
Classifier: Programming Language :: Python :: 3
Classifier: Programming Language :: Python :: 3.10
Classifier: Programming Language :: Python :: 3.11
Classifier: Programming Language :: Python :: 3.12
Requires-Dist: Pillow (>=9.3.0,<10.0.0)
Requires-Dist: PyYAML (>=6.0,<7.0)
Requires-Dist: Telethon (==1.26.0)
Requires-Dist: aiohttp (>=3.8.3,<4.0.0)
Requires-Dist: cryptg (>=0.4.0,<0.5.0)
Requires-Dist: gallery-dl (>=1.26.2,<2.0.0)
Requires-Dist: hachoir (>=3.1.3,<4.0.0)
Requires-Dist: pydantic (>=1.10.2,<2.0.0)
Requires-Dist: pymongo (>=4.3.3,<5.0.0)
Requires-Dist: pytesseract (>=0.3.7,<0.4.0)
Requires-Dist: python-dotenv (>=0.21.0,<0.22.0)
Requires-Dist: requests (>=2.28.1,<3.0.0)
Requires-Dist: rich (>=12.6.0,<13.0.0)
Requires-Dist: streamlit (>=1.15.2,<2.0.0)
Requires-Dist: typer (>=0.7.0,<0.8.0)
Requires-Dist: verlat (>=0.1.0,<0.2.0)
Requires-Dist: watermark.py (>=0.0.3,<0.0.4)
Project-URL: Documentation, https://github.com/aahnik/tgcf/wiki
Project-URL: Repository, https://github.com/aahnik/tgcf
